fon/__init__.py
fon/functional.py
fon/list.py
fon/maths.py
fon/string.py
fon-0.0.1.dist-info/METADATA
fon-0.0.1.dist-info/WHEEL
fon-0.0.1.dist-info/licenses/LICENSE
fon-0.0.1.dist-info/RECORD
