Metadata-Version: 2.1
Name: fon
Version: 0.0.1
Summary: Functional tools, inspired by Haskell.
Project-URL: Homepage, https://github.com/gate-max/fm
Project-URL: Bug Tracker, https://github.com/gate-max/fm/issues
Author-email: Chris Sze <chris_sze@yahoo.com>
License: MIT License
Classifier: License :: OSI Approved :: MIT License
Classifier: Operating System :: OS Independent
Classifier: Programming Language :: Python :: 3
Requires-Python: >=3.7
